mc_goods/__init__.py
mc_goods/_version.py
mc_goods/cbofs-rgrid.yaml
mc_goods/cbofs.yaml
mc_goods/ciofs-rgrid.yaml
mc_goods/ciofs.yaml
mc_goods/creofs-rgrid.yaml
mc_goods/creofs.yaml
mc_goods/dbofs-rgrid.yaml
mc_goods/dbofs.yaml
mc_goods/gfs-1-2deg.yaml
mc_goods/gfs-1-4deg.yaml
mc_goods/gfs-1deg.yaml
mc_goods/gofs.yaml
mc_goods/gomofs-2ds.yaml
mc_goods/gomofs-rgrid.yaml
mc_goods/gomofs.yaml
mc_goods/leofs-rgrid.yaml
mc_goods/leofs.yaml
mc_goods/lmhofs-rgrid.yaml
mc_goods/lmhofs.yaml
mc_goods/loofs-fvcom.yaml
mc_goods/loofs.yaml
mc_goods/lsofs-fvcom.yaml
mc_goods/lsofs.yaml
mc_goods/ngofs2-2ds.yaml
mc_goods/ngofs2-rgrid.yaml
mc_goods/ngofs2.yaml
mc_goods/nyofs.yaml
mc_goods/rtofs-2d.yaml
mc_goods/rtofs-ak.yaml
mc_goods/rtofs-east.yaml
mc_goods/rtofs-west.yaml
mc_goods/rtofs.yaml
mc_goods/sfbofs-rgrid.yaml
mc_goods/sfbofs.yaml
mc_goods/tbofs-rgrid.yaml
mc_goods/tbofs.yaml
mc_goods/wcofs-2ds.yaml
mc_goods/wcofs-rgrid.yaml
mc_goods/wcofs.yaml
mc_goods/boundaries/cbofs.yaml
mc_goods/boundaries/cbofs_rgrid.yaml
mc_goods/boundaries/ciofs.yaml
mc_goods/boundaries/ciofs_rgrid.yaml
mc_goods/boundaries/creofs.yaml
mc_goods/boundaries/creofs_rgrid.yaml
mc_goods/boundaries/dbofs.yaml
mc_goods/boundaries/dbofs_rgrid.yaml
mc_goods/boundaries/gfs_1_2deg.yaml
mc_goods/boundaries/gfs_1_4deg.yaml
mc_goods/boundaries/gfs_1deg.yaml
mc_goods/boundaries/gofs.yaml
mc_goods/boundaries/gomofs.yaml
mc_goods/boundaries/gomofs_2ds.yaml
mc_goods/boundaries/gomofs_rgrid.yaml
mc_goods/boundaries/leofs.yaml
mc_goods/boundaries/leofs_rgrid.yaml
mc_goods/boundaries/lmhofs.yaml
mc_goods/boundaries/lmhofs_rgrid.yaml
mc_goods/boundaries/loofs.yaml
mc_goods/boundaries/loofs_fvcom.yaml
mc_goods/boundaries/lsofs.yaml
mc_goods/boundaries/lsofs_fvcom.yaml
mc_goods/boundaries/ngofs2.yaml
mc_goods/boundaries/ngofs2_2ds.yaml
mc_goods/boundaries/ngofs2_rgrid.yaml
mc_goods/boundaries/nyofs.yaml
mc_goods/boundaries/rtofs.yaml
mc_goods/boundaries/rtofs_2d.yaml
mc_goods/boundaries/rtofs_ak.yaml
mc_goods-1.1.1.dist-info/LICENSE.txt
mc_goods-1.1.1.dist-info/METADATA
mc_goods-1.1.1.dist-info/WHEEL
mc_goods-1.1.1.dist-info/entry_points.txt
mc_goods-1.1.1.dist-info/top_level.txt
mc_goods-1.1.1.dist-info/RECORD
