Metadata-Version: 2.1
Name: mc-goods
Version: 1.1.1
Summary: model_catalogs catalogs for GOODS
Home-page: https://github.com/axiom-data-science/mc-goods
Author: Axiom Data Science
Author-email: kristen@axds.co
License: MIT
Classifier: Development Status :: 5 - Production/Stable
Classifier: Topic :: Scientific/Engineering
Classifier: Intended Audience :: Science/Research
Classifier: Operating System :: OS Independent
Classifier: Programming Language :: Python
Classifier: Programming Language :: Python :: 3
Classifier: Programming Language :: Python :: 3.8
Classifier: Programming Language :: Python :: 3.9
Classifier: Programming Language :: Python :: 3.10
Classifier: License :: OSI Approved :: MIT License
Requires-Python: >=3.6
License-File: LICENSE.txt
Requires-Dist: intake
Requires-Dist: numpy
Requires-Dist: requests
